nolink_connector/__init__.py
nolink_connector/auto_start.py
nolink_connector/detector.py
nolink_connector/main.py
nolink_connector/security.py
nolink_connector/server.py
nolink_connector/terminal.py
nolink_connector-1.1.0.dist-info/licenses/LICENSE
nolink_connector-1.1.0.dist-info/METADATA
nolink_connector-1.1.0.dist-info/WHEEL
nolink_connector-1.1.0.dist-info/entry_points.txt
nolink_connector-1.1.0.dist-info/top_level.txt
nolink_connector-1.1.0.dist-info/RECORD
