Metadata-Version: 2.4
Name: nolink-connector
Version: 1.1.0
Summary: Auto-detecting Socket.IO Terminal Bridge for web platforms
Home-page: https://github.com/Sumedh99/nolink-connector
Author: Sumedh Patil
Author-email: Sumedh Patil <sumedhpatil99@gmail.com>
License: MIT License
Project-URL: Homepage, https://github.com/Sumedh99/nolink-connector
Project-URL: Repository, https://github.com/Sumedh99/nolink-connector
Project-URL: Issues, https://github.com/Sumedh99/nolink-connector/issues
Project-URL: Documentation, https://github.com/Sumedh99/nolink-connector#readme
Keywords: terminal,socketio,web,bridge,automation,shell
Classifier: Development Status :: 5 - Production/Stable
Classifier: Intended Audience :: Developers
Classifier: License :: OSI Approved :: MIT License
Classifier: Operating System :: OS Independent
Classifier: Programming Language :: Python :: 3.8
Classifier: Programming Language :: Python :: 3.9
Classifier: Programming Language :: Python :: 3.10
Classifier: Programming Language :: Python :: 3.11
Classifier: Programming Language :: Python :: 3.12
Classifier: Topic :: Software Development :: Libraries :: Python Modules
Classifier: Topic :: System :: System Shells
Classifier: Topic :: Internet :: WWW/HTTP :: Dynamic Content
Requires-Python: >=3.8
License-File: LICENSE
Requires-Dist: python-socketio[client]==5.8.0
Requires-Dist: aiohttp==3.8.5
Requires-Dist: psutil==5.9.5
Requires-Dist: pexpect==4.8.0; platform_system != "Windows"
Requires-Dist: pywinpty==2.0.12; platform_system == "Windows"
Requires-Dist: cryptography==41.0.0
Requires-Dist: asyncpg==0.28.0
Requires-Dist: python-dotenv==1.0.0
Requires-Dist: colorama==0.4.6
Requires-Dist: click==8.1.6
Dynamic: author
Dynamic: home-page
Dynamic: license-file
Dynamic: requires-python
